[
  {
    "task": 13,
    "path": "scripts/golf/loop_7999_13/lane_scalarize_uniform_wave16/task013_r01.onnx",
    "exit_code": 0,
    "result": {
      "task": 13,
      "decision": "ADOPT",
      "cost": 744,
      "lib_gold": true,
      "official_gold": true,
      "margin_stable": true,
      "margin_min": 73.08984375,
      "fresh_total": 5000,
      "fresh_fails": 0,
      "fresh_rate": 1.0,
      "min_fresh_rate": 1.0,
      "fresh_ok": true,
      "path": "/Users/kimura2003/Downloads/projects/Kaggle/Neurogolf/scripts/golf/loop_7999_13/lane_scalarize_uniform_wave16/task013_r01.onnx"
    },
    "runtime_exception": false,
    "stdout": "[\n  {\n    \"task\": 13,\n    \"decision\": \"ADOPT\",\n    \"cost\": 744,\n    \"lib_gold\": true,\n    \"official_gold\": true,\n    \"margin_stable\": true,\n    \"margin_min\": 73.08984375,\n    \"fresh_total\": 5000,\n    \"fresh_fails\": 0,\n    \"fresh_rate\": 1.0,\n    \"min_fresh_rate\": 1.0,\n    \"fresh_ok\": true,\n    \"path\": \"/Users/kimura2003/Downloads/projects/Kaggle/Neurogolf/scripts/golf/loop_7999_13/lane_scalarize_uniform_wave16/task013_r01.onnx\"\n  }\n]\n",
    "stderr_tail": "\nADOPT=1/1\n  task013: ADOPT fresh=0/5000 rate=1.0 threshold=1.0 lib=True off=True margin=73.08984375 cost=744\n"
  }
]
